mock_boto3/__init__.py
mock_boto3/mock_athena.py
mock_boto3/mock_cloudwatch.py
mock_boto3/mock_config.py
mock_boto3/mock_dynamodb.py
mock_boto3/mock_ec2.py
mock_boto3/mock_exceptions.py
mock_boto3/mock_lambda.py
mock_boto3/mock_logs.py
mock_boto3/mock_mwaa.py
mock_boto3/mock_paginator.py
mock_boto3/mock_rds.py
mock_boto3/mock_redshift_data.py
mock_boto3/mock_s3.py
mock_boto3/mock_secrets_manager.py
mock_boto3/mock_security_hub.py
mock_boto3/mock_ssm.py
mock_boto3/mock_stepfunctions.py
mock_boto3/mock_sts.py
mock_boto3/mock_waiter.py
mock_boto3/dynamodb/conditions.py
mock_boto3-0.0.5.dist-info/LICENSE
mock_boto3-0.0.5.dist-info/METADATA
mock_boto3-0.0.5.dist-info/WHEEL
mock_boto3-0.0.5.dist-info/top_level.txt
mock_boto3-0.0.5.dist-info/RECORD
