Metadata-Version: 2.1
Name: mock-boto3
Version: 0.0.5
Summary: mock_boto3
Author-email: johnnyblase <johnnyblasin@gmail.com>
License: MIT License        
Project-URL: Homepage, https://github.com/jadecobra/mock_boto3
Project-URL: Bug Tracker, https://github.com/jadecobra/mock_boto3/issues
Classifier: Programming Language :: Python :: 3
Classifier: License :: OSI Approved :: MIT License
Classifier: Operating System :: OS Independent
Requires-Python: >=3.9
License-File: LICENSE
